{
  "photos": [
    "./1s172.jpg"
  ],
  "body": "Цельная твердосплавная сферическая концевая фреза, 2 зуба, со средней режущей частью, с заниженной шейкой.",
  "coating": "pp",
  "allowanceCuttingDiameter": "h8",
  "scheme": [
    {
      "name": "a",
      "scheme": "sphere-conus-lower-r"
    },
    {
      "name": "b",
      "scheme": "sphere-lower-r"
    }
  ],
  "grooveInclination": [
    37.5
  ],
  "mainUsage": [
    "n"
  ],
  "cuttingPartLength": [
    "short",
    "middle"
  ],
  "endShapes": [
    "sphere"
  ],
  "productCategory": "non-ferrous-alloys",
  "tail": "cylinder",
  "possibleUsage": null,
  "cogs": [
    {
      "cogsPitch": "permanent",
      "cogsNumber": 2
    }
  ],
  "type": "end-mills",
  "id": "1s172",
  "productSeriesSet": "lower R"
}