{
  "photos": [
    "./1c201.jpg"
  ],
  "body": "Цельная твердосплавная концевая фреза, 4 зуба, с короткой режущей частью, с заниженной шейкой.",
  "coating": "ng",
  "allowanceCuttingDiameter": "h8",
  "scheme": [
    {
      "name": "b",
      "scheme": "cylinder-lower-r"
    }
  ],
  "grooveInclination": [
    42,
    45
  ],
  "mainUsage": [
    "m",
    "s"
  ],
  "cuttingPartLength": [
    "short"
  ],
  "endShapes": [
    "rect-sharp",
    "rect-r"
  ],
  "productCategory": "stainless-steel",
  "tail": "cylinder",
  "possibleUsage": [
    "p",
    "k",
    "h1.1"
  ],
  "cogs": [
    {
      "cogsNumber": 4,
      "cogsPitch": "variable"
    }
  ],
  "cogsPitch": "variable",
  "cogsNumber": [
    4
  ],
  "type": "end-mills",
  "id": "1c201",
  "productSeriesSet": "lower R"
}